{"cameraMode":{"drawMode":0,"name":"Shaded","section":"Shading Mode"},"sceneLighting":true,"audioPlay":false,"sceneViewState":{"m_AlwaysRefresh":false,"showFog":true,"showSkybox":true,"showFlares":true,"showImageEffects":true,"showParticleSystems":true,"showVisualEffectGraphs":true,"m_FxEnabled":true},"in2DMode":false,"pivot":{"x":20.22925567626953,"y":-0.7393655776977539,"z":68.80598449707031},"rotation":{"x":-0.14887186884880067,"y":-0.7777402400970459,"z":0.20073841512203217,"w":-0.5767800211906433},"size":9.977825164794922,"orthographic":false}